{"accountEnabled":true,"signInNames":[{"type":"emailAddress","value":"Etnis.Mun@WigiTech.com"}],"creationType":"LocalAccount","displayName":"Etnis Mun","mailNickname":"Etnis.Mun","passwordProfile":{"password":"P@ssword!","forceChangePasswordNextLogin":false},"passwordPolicies":"DisablePasswordExpiration","city":"WATERTOWN","country":"US","facsimileTelephoneNumber":null,"givenName":"Etnis","mail":null,"mobile":"9785551212","otherMails":[],"postalCode":"02452","preferredLanguage":null,"state":"MA","streetAddress":"9 GALEN STREEET","surname":"Mun","telephoneNumber":"9785551212"}
